toki_pybind.cpython-37m-x86_64-linux-gnu.so
toki/__init__.py
toki/version.py
toki/Toki.py
toki/config/config.ini
toki/config/abbrevs.txt
toki/config/segment.srx
pytoki-0.1.2.data/data/config/example.ini
pytoki-0.1.2.data/data/config/general.ini
pytoki-0.1.2.data/data/config/tok-agg1.txt
pytoki-0.1.2.data/data/config/tok-agg-sg2.txt
pytoki-0.1.2.data/data/config/nkjp.ini
pytoki-0.1.2.data/data/config/tok-agg-pl.txt
pytoki-0.1.2.data/data/config/config.ini
pytoki-0.1.2.data/data/config/abbrevs.txt
pytoki-0.1.2.data/data/config/tok-agg-sgn.txt
pytoki-0.1.2.data/data/config/ikipi-tok.ini
pytoki-0.1.2.data/data/config/segment.srx
pytoki-0.1.2.data/data/config/sample.ini
.libstoki_pybind/libgmodule-2-bac48ce7.0.so.0.2800.8
.libstoki_pybind/libz-eb09ad1d.so.1.2.3
.libstoki_pybind/libboost_program_options-42e9bdcc.so.1.65.1
.libstoki_pybind/libpwrutils-6967b44e.so.1.0
.libstoki_pybind/libicui18n-6ab72f54.so.42.1
.libstoki_pybind/libxml2-e04a0072.so.2.7.6
.libstoki_pybind/libboost_system-3ba94d8f.so.1.65.1
.libstoki_pybind/libsigc-2-cbd0a7b6.0.so.0.0.0
.libstoki_pybind/libtoki-cbf53b62.so.1.1
.libstoki_pybind/libxml++-2-74809510.6.so.2.0.7
.libstoki_pybind/libglibmm-2-047e5b3d.4.so.1.2.0
.libstoki_pybind/libicuio-5ef5735c.so.42.1
.libstoki_pybind/libloki-6f44841e.so.0.1.7
.libstoki_pybind/libboost_filesystem-3d5b6da8.so.1.65.1
.libstoki_pybind/libboost_regex-4821eb22.so.1.65.1
.libstoki_pybind/libicudata-13dff365.so.42.1
.libstoki_pybind/libboost_iostreams-e5bb90a7.so.1.65.1
.libstoki_pybind/libicuuc-8a9b26fa.so.42.1
pytoki-0.1.2.dist-info/RECORD
pytoki-0.1.2.dist-info/WHEEL
pytoki-0.1.2.dist-info/METADATA
pytoki-0.1.2.dist-info/top_level.txt
