Metadata-Version: 2.1
Name: pytoki
Version: 0.1.2
Summary: toki Python bindings
Home-page: UNKNOWN
Author: Tomasz Grzegorzek
Author-email: tomasz.grzegorzek@alphamoon.ai
Maintainer: Tomasz Grzegorzek
Maintainer-email: dev@alphamoon.ai
License: MIT
Platform: UNKNOWN
Classifier: Development Status :: 3 - Alpha
Classifier: Intended Audience :: Developers
Classifier: Intended Audience :: Science/Research
Classifier: License :: OSI Approved :: MIT License
Classifier: Programming Language :: Python :: 2.7
Classifier: Programming Language :: Python :: 3.4
Classifier: Programming Language :: Python :: 3.5
Classifier: Programming Language :: Python :: 3.6
Classifier: Programming Language :: Python :: 3.7
Classifier: Topic :: Software Development
Classifier: Topic :: Scientific/Engineering
Classifier: Operating System :: POSIX
Classifier: Operating System :: Unix
Requires-Dist: pybind11 (>=2.2)
Requires-Dist: setuptools (>=0.7.0)
